{
  "version": "7",
  "dialect": "postgresql",
  "entries": [
    {
      "idx": 0,
      "version": "7",
      "when": 1784241073608,
      "tag": "0000_melodic_shaman",
      "breakpoints": true
    },
    {
      "idx": 1,
      "version": "7",
      "when": 1784242796221,
      "tag": "0001_cultured_king_bedlam",
      "breakpoints": true
    },
    {
      "idx": 2,
      "version": "7",
      "when": 1784244261579,
      "tag": "0002_typical_naoko",
      "breakpoints": true
    },
    {
      "idx": 3,
      "version": "7",
      "when": 1784270212697,
      "tag": "0003_bitter_piledriver",
      "breakpoints": true
    },
    {
      "idx": 4,
      "version": "7",
      "when": 1784272425146,
      "tag": "0004_petite_hellfire_club",
      "breakpoints": true
    },
    {
      "idx": 5,
      "version": "7",
      "when": 1784274684165,
      "tag": "0005_smiling_kid_colt",
      "breakpoints": true
    },
    {
      "idx": 6,
      "version": "7",
      "when": 1784276095961,
      "tag": "0006_next_susan_delgado",
      "breakpoints": true
    },
    {
      "idx": 7,
      "version": "7",
      "when": 1784277926134,
      "tag": "0007_left_firestar",
      "breakpoints": true
    }
  ]
}